orpheusmusictransformer/TMIDIX.py
orpheusmusictransformer/__init__.py
orpheusmusictransformer/midi_processors.py
orpheusmusictransformer/midi_to_colab_audio.py
orpheusmusictransformer/model_loader.py
orpheusmusictransformer/models.py
orpheusmusictransformer/orpheusmusictransformer.py
orpheusmusictransformer/sample_midis.py
orpheusmusictransformer/x_transformer_1_23_2.py
orpheusmusictransformer/examples/README.md
orpheusmusictransformer/examples/__init__.py
orpheusmusictransformer/seed_midis/Orpheus-Music-Transformer-MI-Seed-1.mid
orpheusmusictransformer/seed_midis/Orpheus-Music-Transformer-MI-Seed-2.mid
orpheusmusictransformer/seed_midis/Orpheus-Music-Transformer-MI-Seed-3.mid
orpheusmusictransformer/seed_midis/Orpheus-Music-Transformer-MI-Seed-4.mid
orpheusmusictransformer/seed_midis/Orpheus-Music-Transformer-MI-Seed-5.mid
orpheusmusictransformer/seed_midis/Orpheus-Music-Transformer-MI-Seed-6.mid
orpheusmusictransformer/seed_midis/Orpheus-Music-Transformer-MI-Seed-7.mid
orpheusmusictransformer/seed_midis/Orpheus-Music-Transformer-Piano-Seed-1.mid
orpheusmusictransformer/seed_midis/Orpheus-Music-Transformer-Piano-Seed-2.mid
orpheusmusictransformer/seed_midis/Orpheus-Music-Transformer-Piano-Seed-3.mid
orpheusmusictransformer/seed_midis/Orpheus-Music-Transformer-Piano-Seed-4.mid
orpheusmusictransformer/seed_midis/Orpheus-Music-Transformer-Piano-Seed-5.mid
orpheusmusictransformer/seed_midis/Orpheus-Music-Transformer-Piano-Seed-6.mid
orpheusmusictransformer/seed_midis/README.md
orpheusmusictransformer/seed_midis/__init__.py
orpheusmusictransformer-0.0.2.dist-info/LICENSE
orpheusmusictransformer-0.0.2.dist-info/METADATA
orpheusmusictransformer-0.0.2.dist-info/WHEEL
orpheusmusictransformer-0.0.2.dist-info/top_level.txt
orpheusmusictransformer-0.0.2.dist-info/RECORD
