Metadata-Version: 2.1
Name: orpheusmusictransformer
Version: 0.0.2
Summary: New SOTA multi-instrumental music transformer with advanced ultra-efficient full MIDI encoding, chords tokens and intro/outro tokens
Home-page: https://github.com/asigalov61/orpheusmusictransformer
Author: Alex Lev
Author-email: Alex Lev <alexlev61@proton.me>
Maintainer-email: Alex Lev <alexlev61@proton.me>
License: Apache Software License 2.0
Project-URL: Homepage, https://github.com/asigalov61/orpheusmusictransformer
Project-URL: Examples, https://github.com/asigalov61/tegridymidi/orpheusmusictransformer/examples
Project-URL: Documentation, https://github.com/asigalov61/orpheusmusictransformer/docs
Project-URL: Repository, https://github.com/asigalov61/Orpheus-Music-Transformer
Project-URL: Issues, https://github.com/asigalov61/orpheusmusictransformer/issues
Project-URL: Discussions, https://github.com/asigalov61/orpheusmusictransformer/discussions
Project-URL: Models, https://huggingface.co/asigalov61/Orpheus-Music-Transformer
Project-URL: Demo, https://huggingface.co/spaces/asigalov61/Orpheus-Music-Transformer
Keywords: MIDI,music,music ai,music transformer,artificial instelligence,orpheus
Classifier: Development Status :: 5 - Production/Stable
Classifier: Intended Audience :: Science/Research
Classifier: Topic :: Multimedia :: Sound/Audio :: MIDI
Classifier: License :: OSI Approved :: Apache Software License
Classifier: Operating System :: OS Independent
Classifier: Programming Language :: Python :: 3.6
Classifier: Programming Language :: Python :: 3.7
Classifier: Programming Language :: Python :: 3.8
Classifier: Programming Language :: Python :: 3.9
Classifier: Programming Language :: Python :: 3.10
Classifier: Programming Language :: Python :: 3.11
Classifier: Programming Language :: Python :: 3.12
Requires-Python: >=3.6
License-File: LICENSE
Requires-Dist: tqdm
Requires-Dist: matplotlib
Requires-Dist: torch
Requires-Dist: einops
Requires-Dist: torch-summary
Requires-Dist: hf-transfer
Requires-Dist: huggingface_hub
Requires-Dist: ipywidgets
